test_linemate_scraper/__init__.py
test_linemate_scraper/scraper.py
test_linemate_scraper-0.1.0.dist-info/LICENSE
test_linemate_scraper-0.1.0.dist-info/METADATA
test_linemate_scraper-0.1.0.dist-info/WHEEL
test_linemate_scraper-0.1.0.dist-info/top_level.txt
test_linemate_scraper-0.1.0.dist-info/RECORD
